[
    {
        "_id": "eVTXPUF4Oz4",
        "title": "In The End  - Linkin Park",
        "img": {
            "url": "https://i.ytimg.com/vi/eVTXPUF4Oz4/default.jpg",
            "width": 120,
            "height": 90
        },
        "artist": "Linkin Park",
        "likedByUsers": [
            {
                "_id": "63331df027123045a3033fbc",
                "username": "Alexorcizet",
                "LikedAt": "9/27/2022"
            }
        ],
        "duration": {
            "hours": 0,
            "min": 3,
            "sec": 39
        }
    },
    {
        "_id": "kXYiU_JCYtU",
        "title": "Numb  - Linkin Park",
        "img": {
            "url": "https://i.ytimg.com/vi/kXYiU_JCYtU/default.jpg",
            "width": 120,
            "height": 90
        },
        "artist": "Linkin Park",
        "likedByUsers": [
            {
                "_id": "63331df027123045a3033fbc",
                "username": "Alexorcizet",
                "LikedAt": "9/27/2022"
            }
        ],
        "duration": {
            "hours": 0,
            "min": 3,
            "sec": 7
        }
    },
    {
        "_id": "Gd9OhYroLN0",
        "title": "Crawling  - Linkin Park",
        "img": {
            "url": "https://i.ytimg.com/vi/Gd9OhYroLN0/default.jpg",
            "width": 120,
            "height": 90
        },
        "artist": "Linkin Park",
        "likedByUsers": [
            {
                "_id": "63331df027123045a3033fbc",
                "username": "Alexorcizet",
                "LikedAt": "9/27/2022"
            }
        ],
        "duration": {
            "hours": 0,
            "min": 3,
            "sec": 37
        }
    },
    {
        "_id": "IbRwSI8yi1o",
        "title": "*NSYNC - Gone",
        "img": {
            "url": "https://i.ytimg.com/vi/IbRwSI8yi1o/default.jpg",
            "width": 120,
            "height": 90
        },
        "artist": "NSYNCVEVO",
        "likedByUsers": [
            {
                "_id": "63331df027123045a3033fbc",
                "username": "Alexorcizet",
                "LikedAt": "9/27/2022"
            }
        ],
        "duration": {
            "hours": 0,
            "min": 5,
            "sec": 7
        }
    },
    {
        "_id": "RF0HhrwIwp0",
        "img": {
            "url": "https://i.ytimg.com/vi/RF0HhrwIwp0/default.jpg",
            "width": 120,
            "height": 90
        },
        "title": "Kings Of Leon - Sex on Fire",
        "artist": "kings of leon",
        "duration": {
            "hours": 0,
            "min": 3,
            "sec": 27
        },
        "addedAt": 1663743790,
        "likedByUsers": [
            {
                "_id": "63331df027123045a3033fbc",
                "username": "Alexorcizet",
                "LikedAt": "9/27/2022"
            }
        ]
    },
    {
        "_id" : "A1OqtIqzScI",
        "img" : {
            "url" : "https://i.ytimg.com/vi/A1OqtIqzScI/default.jpg",
            "width" : 120,
            "height" : 90
        },
        "title" : "Green Day - Holiday",
        "artist" : "Green Day",
        "duration" : {
            "hours" : 0,
            "min" : 4,
            "sec" : 41
        },
        "likedByUsers" : [
            {
                "_id": "63331df027123045a3033fbc",
                "username": "Alexorcizet",
                "LikedAt": "9/27/2022"
            }
        ]
    }
]